contacts24/__init__.py
contacts24/__main__.py
contacts24/birthdays.py
contacts24/cli.py
contacts24/cli_commands.py
contacts24/config.py
contacts24/contacts.py
contacts24/db.py
contacts24/errors.py
contacts24/models/address_book.py
contacts24/models/note.py
contacts24/models/notes.py
contacts24/models/record.py
contacts24/notes_functions.py
contacts24/os_resources.py
contacts24/serialization_helper.py
contacts24-24.3.17.dist-info/METADATA
contacts24-24.3.17.dist-info/WHEEL
contacts24-24.3.17.dist-info/entry_points.txt
contacts24-24.3.17.dist-info/RECORD
