Metadata-Version: 2.1
Name: contacts24
Version: 24.3.17
Summary: 
Author: Vitaliy Kononenko
Author-email: konvio@users.noreply.github.com
Requires-Python: >=3.11,<4.0
Classifier: Programming Language :: Python :: 3
Classifier: Programming Language :: Python :: 3.11
Classifier: Programming Language :: Python :: 3.12
Requires-Dist: colorama (>=0.4.6,<0.5.0)
Requires-Dist: prompt-toolkit (>=3.0.43,<4.0.0)
